LICENSE-2.0.txt
MANIFEST.in
README.rst
setup.py
mtk/__init__.py
mtk.egg-info/PKG-INFO
mtk.egg-info/SOURCES.txt
mtk.egg-info/dependency_links.txt
mtk.egg-info/not-zip-safe
mtk.egg-info/top_level.txt
mtk/amqp_0_9_1/__init__.py
mtk/amqp_0_9_1/channel.py
mtk/amqp_0_9_1/connection.py
mtk/amqp_0_9_1/error.py
mtk/amqp_0_9_1/frame.py
mtk/amqp_0_9_1/mechanism.py
mtk/amqp_0_9_1/table.py
mtk/amqp_0_9_1/util.py
mtk/amqp_0_9_1/gen/__init__.py
mtk/amqp_0_9_1/gen/constants.py
mtk/amqp_0_9_1/gen/methods.py
mtk/amqp_0_9_1/gen/Basic/Ack.py
mtk/amqp_0_9_1/gen/Basic/Cancel.py
mtk/amqp_0_9_1/gen/Basic/CancelOk.py
mtk/amqp_0_9_1/gen/Basic/Consume.py
mtk/amqp_0_9_1/gen/Basic/ConsumeOk.py
mtk/amqp_0_9_1/gen/Basic/Deliver.py
mtk/amqp_0_9_1/gen/Basic/Get.py
mtk/amqp_0_9_1/gen/Basic/GetEmpty.py
mtk/amqp_0_9_1/gen/Basic/GetOk.py
mtk/amqp_0_9_1/gen/Basic/Publish.py
mtk/amqp_0_9_1/gen/Basic/Qos.py
mtk/amqp_0_9_1/gen/Basic/QosOk.py
mtk/amqp_0_9_1/gen/Basic/Recover.py
mtk/amqp_0_9_1/gen/Basic/RecoverAsync.py
mtk/amqp_0_9_1/gen/Basic/RecoverOk.py
mtk/amqp_0_9_1/gen/Basic/Reject.py
mtk/amqp_0_9_1/gen/Basic/Return.py
mtk/amqp_0_9_1/gen/Basic/__init__.py
mtk/amqp_0_9_1/gen/Channel/Close.py
mtk/amqp_0_9_1/gen/Channel/CloseOk.py
mtk/amqp_0_9_1/gen/Channel/Flow.py
mtk/amqp_0_9_1/gen/Channel/FlowOk.py
mtk/amqp_0_9_1/gen/Channel/Open.py
mtk/amqp_0_9_1/gen/Channel/OpenOk.py
mtk/amqp_0_9_1/gen/Channel/__init__.py
mtk/amqp_0_9_1/gen/Connection/Close.py
mtk/amqp_0_9_1/gen/Connection/CloseOk.py
mtk/amqp_0_9_1/gen/Connection/Open.py
mtk/amqp_0_9_1/gen/Connection/OpenOk.py
mtk/amqp_0_9_1/gen/Connection/Secure.py
mtk/amqp_0_9_1/gen/Connection/SecureOk.py
mtk/amqp_0_9_1/gen/Connection/Start.py
mtk/amqp_0_9_1/gen/Connection/StartOk.py
mtk/amqp_0_9_1/gen/Connection/Tune.py
mtk/amqp_0_9_1/gen/Connection/TuneOk.py
mtk/amqp_0_9_1/gen/Connection/__init__.py
mtk/amqp_0_9_1/gen/Exchange/Declare.py
mtk/amqp_0_9_1/gen/Exchange/DeclareOk.py
mtk/amqp_0_9_1/gen/Exchange/Delete.py
mtk/amqp_0_9_1/gen/Exchange/DeleteOk.py
mtk/amqp_0_9_1/gen/Exchange/__init__.py
mtk/amqp_0_9_1/gen/Queue/Bind.py
mtk/amqp_0_9_1/gen/Queue/BindOk.py
