Metadata-Version: 1.1
Name: mtk
Version: 1.0b1
Summary: The Messaging ToolKit
Home-page: https://bitbucket.org/wwsmith/mtk
Author: Warren Smith
Author-email: wsmith@tacc.utexas.edu
License: Apache
Keywords: messaging publish subscribe amqu
Platform: UNKNOWN
Classifier: Development Status :: 4 - Beta
Classifier: License :: OSI Approved :: Apache Software License
Classifier: Programming Language :: Python :: 2
Classifier: Topic :: Communications
